lakefs_sdk/__init__.py
lakefs_sdk/api_client.py
lakefs_sdk/api_response.py
lakefs_sdk/client.py
lakefs_sdk/configuration.py
lakefs_sdk/exceptions.py
lakefs_sdk/py.typed
lakefs_sdk/rest.py
lakefs_sdk/api/__init__.py
lakefs_sdk/api/actions_api.py
lakefs_sdk/api/auth_api.py
lakefs_sdk/api/branches_api.py
lakefs_sdk/api/commits_api.py
lakefs_sdk/api/config_api.py
lakefs_sdk/api/experimental_api.py
lakefs_sdk/api/external_api.py
lakefs_sdk/api/health_check_api.py
lakefs_sdk/api/import_api.py
lakefs_sdk/api/internal_api.py
lakefs_sdk/api/license_api.py
lakefs_sdk/api/metadata_api.py
lakefs_sdk/api/objects_api.py
lakefs_sdk/api/pulls_api.py
lakefs_sdk/api/refs_api.py
lakefs_sdk/api/remotes_api.py
lakefs_sdk/api/repositories_api.py
lakefs_sdk/api/staging_api.py
lakefs_sdk/api/tags_api.py
lakefs_sdk/models/__init__.py
lakefs_sdk/models/abort_presign_multipart_upload.py
lakefs_sdk/models/access_key_credentials.py
lakefs_sdk/models/acl.py
lakefs_sdk/models/action_run.py
lakefs_sdk/models/action_run_list.py
lakefs_sdk/models/async_task_status.py
lakefs_sdk/models/auth_capabilities.py
lakefs_sdk/models/authentication_token.py
lakefs_sdk/models/branch_creation.py
lakefs_sdk/models/branch_protection_rule.py
lakefs_sdk/models/capabilities_config.py
lakefs_sdk/models/cherry_pick_creation.py
lakefs_sdk/models/comm_prefs_input.py
lakefs_sdk/models/commit.py
lakefs_sdk/models/commit_async_status.py
lakefs_sdk/models/commit_creation.py
lakefs_sdk/models/commit_list.py
lakefs_sdk/models/commit_overrides.py
lakefs_sdk/models/commit_record_creation.py
lakefs_sdk/models/complete_presign_multipart_upload.py
lakefs_sdk/models/config.py
lakefs_sdk/models/copy_part_source.py
lakefs_sdk/models/credentials.py
lakefs_sdk/models/credentials_list.py
lakefs_sdk/models/credentials_with_secret.py
lakefs_sdk/models/current_user.py
lakefs_sdk/models/custom_viewer.py
lakefs_sdk/models/diff.py
lakefs_sdk/models/diff_list.py
lakefs_sdk/models/diff_object_stat.py
lakefs_sdk/models/error.py
lakefs_sdk-1.76.0.dist-info/METADATA
lakefs_sdk-1.76.0.dist-info/WHEEL
lakefs_sdk-1.76.0.dist-info/top_level.txt
lakefs_sdk-1.76.0.dist-info/RECORD
