Metadata-Version: 2.4
Name: lakefs-sdk
Version: 1.76.0
Summary: lakeFS API
Home-page: https://github.com/treeverse/lakeFS/tree/master/clients/python
Author: Treeverse
Author-email: services@treeverse.io
License: Apache 2.0
Keywords: OpenAPI,OpenAPI-Generator,lakeFS API
Requires-Python: >=3.6
Requires-Dist: urllib3<3.0.0,>=1.25.3
Requires-Dist: python-dateutil
Requires-Dist: pydantic>=1.10.5
Requires-Dist: aenum
Dynamic: author
Dynamic: author-email
Dynamic: description
Dynamic: description-content-type
Dynamic: home-page
Dynamic: keywords
Dynamic: license
Dynamic: requires-dist
Dynamic: requires-python
Dynamic: summary
